LICENSE
MANIFEST.in
README.md
requirements-dev.txt
requirements.txt
setup.cfg
setup.py
scripts/txt2pdf
tests/__init__.py
tests/defaults.py
tests/test_cli.py
tests/test_core.py
txt2pdf/__init__.py
txt2pdf/core.py
txt2pdf/exceptions.py
txt2pdf/pdfgenerator.py
txt2pdf.egg-info/PKG-INFO
txt2pdf.egg-info/SOURCES.txt
txt2pdf.egg-info/dependency_links.txt
txt2pdf.egg-info/requires.txt
txt2pdf.egg-info/top_level.txt