Metadata-Version: 2.1
Name: txt2pdf
Version: 0.6.2
Summary: txt2pdf, a Markdown to PDF conversion tool
Home-page: UNKNOWN
Author: Julien Maupetit & c4ffein
Author-email: c4ffein@gmail.com
License: MIT
Keywords: markdown converter css pdf
Platform: UNKNOWN
Classifier: Development Status :: 5 - Production/Stable
Classifier: Intended Audience :: Customer Service
Classifier: Intended Audience :: End Users/Desktop
Classifier: Intended Audience :: Information Technology
Classifier: Intended Audience :: Science/Research
Classifier: Intended Audience :: Other Audience
Classifier: License :: OSI Approved :: MIT License
Classifier: Environment :: Console
Classifier: Operating System :: MacOS
Classifier: Operating System :: Microsoft :: Windows
Classifier: Operating System :: POSIX
Classifier: Programming Language :: Python :: 3
Classifier: Programming Language :: Python :: 3.6
Classifier: Programming Language :: Python :: 3.7
Classifier: Programming Language :: Python :: 3.8
Classifier: Topic :: Office/Business
Classifier: Topic :: Utilities
License-File: LICENSE
